calculadora/__init__.py
calculadora/funcoes.py
meu_primeiro_pacote_exemplo-0.1.0.dist-info/METADATA
meu_primeiro_pacote_exemplo-0.1.0.dist-info/WHEEL
meu_primeiro_pacote_exemplo-0.1.0.dist-info/top_level.txt
meu_primeiro_pacote_exemplo-0.1.0.dist-info/RECORD
