Metadata-Version: 2.4
Name: meu_primeiro_pacote_exemplo
Version: 0.1.0
Summary: Um pacote de calculadora simples
Home-page: https://github.com/Cempressa
Author: Seu Nome
Author-email: marcos.luiz@gmx.us
Requires-Python: >=3.6
Dynamic: author
Dynamic: author-email
Dynamic: description-content-type
Dynamic: home-page
Dynamic: requires-python
Dynamic: summary
